{
  "completed_games": 20,
  "timestamp": 1757693441,
  "summary": {
    "summary": {
      "total_games": 20,
      "average_duration": 0.021725142002105714,
      "average_turns": 78.6,
      "win_distribution": {
        "Художник-фрилансер": 4,
        "Предприниматель": 5,
        "Официант": 3,
        "Курьер": 2,
        "Жена/муж испанца": 2,
        "IT-шник": 1,
        "Студент": 2,
        "Пенсионер": 1
      },
      "end_reason_distribution": {
        "win": 20
      }
    },
    "card_usage_summary": {
      "total_cards_played": 1919,
      "cards_by_type": {
        "personal_items": 268,
        "health_cards": 141,
        "housing_cards": 237,
        "green_cards": 1136,
        "white_cards": 137
      },
      "most_used_cards_overall": [
        {
          "card_type": "green_cards",
          "card_id": "documents_09",
          "usage_count": 17,
          "games_appeared": 17
        },
        {
          "card_type": "green_cards",
          "card_id": "mixed_07",
          "usage_count": 17,
          "games_appeared": 17
        },
        {
          "card_type": "green_cards",
          "card_id": "work_08",
          "usage_count": 16,
          "games_appeared": 16
        },
        {
          "card_type": "green_cards",
          "card_id": "documents_02",
          "usage_count": 16,
          "games_appeared": 16
        },
        {
          "card_type": "green_cards",
          "card_id": "work_13",
          "usage_count": 16,
          "games_appeared": 16
        },
        {
          "card_type": "green_cards",
          "card_id": "work_10",
          "usage_count": 16,
          "games_appeared": 16
        },
        {
          "card_type": "green_cards",
          "card_id": "documents_01",
          "usage_count": 16,
          "games_appeared": 16
        },
        {
          "card_type": "green_cards",
          "card_id": "work_12",
          "usage_count": 16,
          "games_appeared": 16
        },
        {
          "card_type": "housing_cards",
          "card_id": "housing_upgrade_02",
          "usage_count": 15,
          "games_appeared": 15
        },
        {
          "card_type": "green_cards",
          "card_id": "documents_boost_01",
          "usage_count": 15,
          "games_appeared": 15
        },
        {
          "card_type": "green_cards",
          "card_id": "mixed_04",
          "usage_count": 15,
          "games_appeared": 15
        },
        {
          "card_type": "green_cards",
          "card_id": "documents_05",
          "usage_count": 15,
          "games_appeared": 15
        },
        {
          "card_type": "green_cards",
          "card_id": "work_09",
          "usage_count": 15,
          "games_appeared": 15
        },
        {
          "card_type": "green_cards",
          "card_id": "mixed_06",
          "usage_count": 15,
          "games_appeared": 15
        },
        {
          "card_type": "green_cards",
          "card_id": "work_02",
          "usage_count": 15,
          "games_appeared": 15
        },
        {
          "card_type": "green_cards",
          "card_id": "boost_courier_special_01",
          "usage_count": 15,
          "games_appeared": 15
        },
        {
          "card_type": "housing_cards",
          "card_id": "housing_upgrade_01",
          "usage_count": 14,
          "games_appeared": 14
        },
        {
          "card_type": "green_cards",
          "card_id": "documents_04",
          "usage_count": 14,
          "games_appeared": 14
        },
        {
          "card_type": "green_cards",
          "card_id": "documents_08",
          "usage_count": 14,
          "games_appeared": 14
        },
        {
          "card_type": "green_cards",
          "card_id": "documents_03",
          "usage_count": 14,
          "games_appeared": 14
        }
      ],
      "unused_cards": {
        "personal_items": [
          "item_22",
          "pensioner_boost_01",
          "item_07",
          "item_31"
        ],
        "health_cards": [
          "health_12",
          "health_30"
        ],
        "housing_cards": [
          "housing_29"
        ],
        "green_cards": [
          "Challenge: Убедить врача в необходимости направления",
          "Challenge: Организовать соседей для давления на управляющую компанию",
          "Challenge: Собрать все справки и пройти всех врачей",
          "Challenge: Предъявить все документы на аренду и показать условия проживания",
          "Challenge: Дозвониться в техподдержку и добиться ремонта",
          "Challenge: Объяснить соседу, что есть закон о тишине",
          "balance_nerf_it_02",
          "Challenge: Попросить соседа играть тише",
          "Challenge: Нужно добраться до аптеки и объяснить симптомы",
          "Challenge: Найти дежурного стоматолога и объяснить проблему",
          "Challenge: Найти лабораторию и правильно сдать анализы",
          "final_balance_artist_boost",
          "doc_level_08"
        ],
        "white_cards": [
          "event_24",
          "event_20"
        ]
      }
    },
    "mechanics_summary": {
      "document_exchanges": {
        "attempts": 0,
        "successes": 0,
        "failures": 0
      },
      "language_challenges": {
        "attempts": 0,
        "successes": 0,
        "failures": 0
      },
      "dice_challenges": {
        "total": 0,
        "health": 0,
        "housing": 0,
        "successes": 0
      },
      "housing_upgrades": {
        "room_to_apartment": 0,
        "apartment_to_mortgage": 0
      },
      "language_upgrades": {
        "basic_to_b1": 0,
        "b1_to_c1": 0
      },
      "money_transactions": {
        "gains": [
          3,
          6,
          3,
          5,
          4,
          5,
          9,
          4,
          3,
          7,
          3,
          5,
          4,
          5,
          9,
          4,
          3,
          5,
          3,
          5,
          4,
          5,
          4,
          4,
          3,
          6,
          3,
          5,
          4,
          5,
          6,
          4,
          3,
          6,
          3,
          5,
          4,
          5,
          6,
          4,
          3,
          5,
          3,
          5,
          4,
          5,
          4,
          4,
          3,
          7,
          3,
          5,
          4,
          5,
          4,
          4,
          5,
          3,
          5,
          4,
          4,
          5,
          4,
          3,
          8,
          3,
          5,
          6,
          4,
          5,
          4,
          3,
          9,
          3,
          5,
          9,
          4,
          5,
          4,
          3,
          8,
          3,
          5,
          4,
          4,
          5,
          4,
          3,
          10,
          3,
          5,
          5,
          4,
          5,
          4,
          3,
          8,
          3,
          5,
          4,
          4,
          5,
          4,
          3,
          5,
          3,
          5,
          6,
          4,
          5,
          4,
          3,
          7,
          3,
          5,
          4,
          4,
          5,
          4,
          3,
          5,
          5,
          4,
          5,
          4,
          3,
          3,
          9,
          5,
          5,
          4,
          8,
          4,
          3,
          3,
          9,
          5,
          5,
          4,
          6,
          4,
          3,
          3,
          6,
          5,
          5,
          4,
          9,
          4,
          3,
          3,
          10,
          5,
          5,
          4,
          4,
          4,
          3,
          3,
          8,
          5,
          5,
          4,
          6,
          4,
          3,
          3,
          9,
          3,
          9,
          5,
          4,
          4,
          9,
          5,
          3,
          3,
          9,
          5,
          4,
          4,
          10,
          5,
          3,
          3,
          9,
          5,
          4,
          4,
          9,
          5,
          3,
          3,
          5,
          5,
          4,
          4,
          10,
          5,
          3,
          3,
          5,
          5,
          4,
          4,
          7,
          5,
          3,
          3,
          8,
          4,
          4,
          7,
          5,
          3,
          3,
          5,
          4,
          4,
          7,
          5,
          3,
          3,
          8,
          4,
          4,
          6,
          5,
          3,
          3,
          8,
          4,
          4,
          5,
          5,
          3,
          3,
          8,
          4,
          4,
          7,
          5,
          3,
          3,
          8,
          4,
          4,
          10,
          5,
          3,
          3,
          6,
          4,
          4,
          6,
          5,
          3,
          3,
          6,
          4,
          4,
          6,
          5,
          3,
          5,
          3,
          9,
          5,
          4,
          4,
          3,
          8,
          5,
          3,
          7,
          5,
          4,
          4,
          3,
          9,
          5,
          3,
          9,
          5,
          4,
          4,
          3,
          7,
          5,
          3,
          8,
          5,
          4,
          4,
          3,
          6,
          5,
          3,
          9,
          5,
          4,
          4,
          3,
          9,
          5,
          3,
          9,
          5,
          4,
          4,
          3,
          9,
          5,
          3,
          7,
          5,
          4,
          4,
          3,
          8,
          5,
          3,
          5,
          5,
          4,
          4,
          3,
          7,
          5,
          3,
          4,
          4,
          5,
          3,
          5,
          5,
          5,
          3,
          4,
          4,
          4,
          3,
          5,
          6,
          5,
          3,
          4,
          4,
          7,
          3,
          5,
          10,
          5,
          3,
          4,
          4,
          4,
          3,
          5,
          6,
          5,
          3,
          4,
          4,
          6,
          3,
          5,
          8,
          5,
          3,
          4,
          4,
          7,
          3,
          5,
          7,
          5,
          3,
          4,
          4,
          3,
          5,
          5,
          5,
          3,
          4,
          4,
          3,
          5,
          7,
          5,
          3,
          4,
          4,
          3,
          5,
          7,
          5,
          3,
          4,
          4,
          3,
          5,
          7,
          5,
          3,
          4,
          4,
          3,
          5,
          10,
          5,
          3,
          4,
          4,
          3,
          5,
          10,
          5,
          3,
          4,
          4,
          3,
          5,
          10,
          4,
          3,
          5,
          9,
          5,
          7,
          3,
          4,
          4,
          3,
          5,
          9,
          5,
          7,
          3,
          4,
          4,
          3,
          5,
          10,
          5,
          5,
          3,
          4,
          4,
          3,
          5,
          6,
          5,
          9,
          3,
          4,
          4,
          3,
          5,
          10,
          5,
          5,
          3,
          4,
          4,
          3,
          5,
          9,
          5,
          7,
          3,
          4,
          4,
          3,
          5,
          8,
          5,
          5,
          3,
          4,
          4,
          3,
          5,
          10,
          5,
          4,
          3,
          4,
          4,
          3,
          5,
          7,
          5,
          9,
          3,
          4,
          4,
          3,
          5,
          8,
          5,
          5,
          3,
          4,
          9,
          5,
          5,
          5,
          4,
          3,
          4,
          3,
          7,
          5,
          7,
          5,
          4,
          3,
          4,
          3,
          7,
          5,
          9,
          5,
          4,
          3,
          4,
          3,
          5,
          5,
          9,
          5,
          4,
          3,
          4,
          3,
          8,
          5,
          6,
          5,
          4,
          3,
          4,
          3,
          4,
          5,
          8,
          5,
          4,
          3,
          4,
          3,
          5,
          5,
          4,
          3,
          7,
          3,
          4,
          5,
          5,
          5,
          4,
          3,
          7,
          3,
          4,
          6,
          5,
          5,
          4,
          3,
          8,
          3,
          4,
          5,
          5,
          5,
          4,
          3,
          4,
          3,
          4,
          7,
          5,
          5,
          4,
          3,
          7,
          3,
          4,
          8,
          5,
          5,
          4,
          3,
          9,
          3,
          4,
          7,
          5,
          5,
          4,
          3,
          9,
          3,
          4,
          6,
          5,
          5,
          4,
          3,
          4,
          3,
          4,
          10,
          5,
          5,
          4,
          3,
          6,
          3,
          4,
          8,
          5,
          5,
          4,
          3,
          9,
          3,
          4,
          6,
          5,
          5,
          4,
          3,
          7,
          3,
          4,
          9,
          5,
          5,
          4,
          3,
          7,
          3,
          4,
          7,
          5,
          5,
          4,
          3,
          4,
          3,
          4,
          7,
          5,
          5,
          4,
          3,
          5,
          3,
          4,
          7,
          5,
          5,
          4,
          3,
          7,
          3,
          4,
          8,
          5,
          5,
          4,
          3,
          7,
          3,
          4,
          7,
          5,
          5,
          4,
          3,
          5,
          3,
          4,
          9,
          5,
          5,
          4,
          3,
          5,
          3,
          4,
          8,
          5,
          5,
          4,
          3,
          6,
          3,
          4,
          6,
          3,
          3,
          4,
          5,
          4,
          5,
          5,
          5,
          3,
          3,
          4,
          5,
          4,
          10,
          5,
          4,
          3,
          3,
          4,
          5,
          4,
          10,
          5,
          4,
          3,
          3,
          4,
          5,
          4,
          7,
          5,
          6,
          3,
          3,
          4,
          5,
          4,
          5,
          5,
          5,
          3,
          3,
          4,
          5,
          4,
          9,
          5,
          4,
          3,
          3,
          4,
          5,
          4,
          5,
          5,
          4,
          3,
          3,
          4,
          5,
          4,
          10,
          5,
          4,
          3,
          3,
          4,
          5,
          4,
          7,
          5,
          5,
          3,
          3,
          4,
          5,
          4,
          8,
          5,
          8,
          3,
          3,
          4,
          5,
          4,
          7,
          5,
          6,
          10,
          9,
          3,
          5,
          4,
          5,
          4,
          3,
          6,
          9,
          3,
          5,
          4,
          5,
          4,
          3,
          6,
          8,
          3,
          5,
          4,
          5,
          4,
          3,
          5,
          5,
          3,
          5,
          4,
          5,
          4,
          3,
          7,
          8,
          3,
          5,
          4,
          5,
          4,
          3,
          6,
          6,
          3,
          5,
          4,
          5,
          4,
          3,
          10,
          4,
          3,
          5,
          4,
          5,
          4,
          3,
          8,
          4,
          3,
          5,
          4,
          5,
          4,
          3,
          3,
          3,
          4,
          6,
          5,
          5,
          4,
          5,
          3,
          3,
          4,
          7,
          9,
          5,
          4,
          5,
          3,
          3,
          4,
          6,
          6,
          5,
          4,
          5,
          3,
          3,
          4,
          9,
          4,
          5,
          4,
          5,
          3,
          3,
          4,
          6,
          7,
          5,
          4,
          5,
          3,
          3,
          4,
          9,
          4,
          5,
          4,
          5,
          3,
          3,
          4,
          7,
          8,
          5,
          4,
          5,
          3,
          3,
          4,
          10,
          8,
          5,
          4,
          5,
          5,
          3,
          4,
          6,
          5,
          3,
          7,
          4,
          5,
          3,
          4,
          4,
          5,
          3,
          8,
          4,
          5,
          3,
          4,
          4,
          5,
          3,
          9,
          4,
          5,
          3,
          4,
          9,
          5,
          3,
          6,
          4,
          5,
          3,
          4,
          8,
          5,
          3,
          9,
          4,
          5,
          3,
          4,
          8,
          5,
          3,
          10,
          4,
          5,
          3,
          4,
          6,
          5,
          3,
          9,
          4,
          5,
          3,
          4,
          5,
          5,
          3,
          7,
          4,
          5,
          3,
          4,
          8,
          5,
          3,
          5,
          4,
          5,
          3,
          4,
          4,
          5,
          3,
          5,
          4,
          4,
          9,
          3,
          5,
          3,
          4,
          7,
          5,
          4,
          7,
          3,
          5,
          3,
          4,
          8,
          5,
          4,
          6,
          3,
          5,
          3,
          4,
          8,
          5,
          4,
          9,
          3,
          5,
          3,
          4,
          6,
          5,
          4,
          5,
          3,
          5,
          3,
          4,
          6,
          5,
          4,
          8,
          3,
          5,
          3,
          4,
          8,
          5,
          4,
          7,
          3,
          5,
          3,
          4,
          4,
          5,
          4,
          6,
          3,
          5,
          3,
          4,
          6,
          5,
          3,
          5,
          5,
          4,
          8,
          4,
          6,
          3,
          3,
          5,
          5,
          4,
          8,
          4,
          9,
          3,
          3,
          5,
          5,
          4,
          4,
          4,
          7,
          3,
          3,
          5,
          5,
          4,
          5,
          4,
          5,
          3,
          3,
          5,
          5,
          4,
          7,
          4,
          6,
          3,
          3,
          5,
          5,
          4,
          8,
          4,
          6,
          3,
          5,
          4,
          9,
          3,
          4,
          9,
          5,
          3,
          5,
          4,
          5,
          3,
          4,
          7,
          5,
          3,
          5,
          4,
          5,
          3,
          4,
          6,
          5,
          3,
          5,
          4,
          10,
          3,
          4,
          4,
          5,
          3,
          5,
          4,
          6,
          3,
          4,
          4,
          5,
          3,
          5,
          4,
          9,
          3,
          4,
          7,
          5,
          3,
          5,
          4,
          7,
          3,
          4,
          9,
          5,
          3,
          5,
          4,
          8,
          3,
          4,
          7,
          5,
          3,
          5,
          4,
          9,
          3,
          4,
          7,
          5,
          3,
          3,
          4,
          5,
          7,
          4,
          5,
          4,
          3,
          3,
          5,
          5,
          7,
          4,
          5,
          4,
          3,
          3,
          5,
          7,
          4,
          5,
          4,
          3,
          3,
          5,
          6,
          4,
          5,
          4,
          3,
          3,
          5,
          8,
          4,
          5,
          4,
          3,
          3,
          5,
          6,
          4,
          5,
          4,
          3,
          3,
          5,
          7,
          4,
          5,
          4,
          3,
          3,
          5,
          6,
          4,
          5,
          4,
          3,
          3,
          5,
          7,
          4,
          5,
          4,
          3,
          3,
          5,
          9,
          4,
          5,
          4,
          3,
          3,
          5,
          9,
          4,
          5,
          4,
          3,
          3,
          4,
          3,
          4,
          5,
          7,
          5,
          6,
          3,
          4,
          3,
          4,
          5,
          9,
          5,
          6,
          3,
          4,
          3,
          4,
          5,
          6,
          5,
          4,
          3,
          4,
          3,
          4,
          5,
          5,
          5,
          9,
          3,
          4,
          3,
          4,
          5,
          10,
          5,
          6,
          3,
          4,
          3,
          4,
          5,
          8,
          5,
          6,
          3,
          4,
          3,
          4,
          5,
          5,
          5,
          5,
          3,
          4,
          3,
          4,
          5,
          10,
          5,
          9,
          3,
          4,
          3,
          4,
          5,
          5,
          5,
          8,
          3,
          4,
          3,
          4,
          5,
          7,
          5,
          5,
          3,
          4,
          3,
          4,
          5,
          10,
          5,
          7,
          4,
          3,
          9,
          5,
          7,
          5,
          3,
          4,
          4,
          3,
          10,
          5,
          9,
          5,
          3,
          4,
          4,
          3,
          6,
          5,
          7,
          5,
          3,
          4,
          4,
          3,
          7,
          5,
          5,
          5,
          3,
          4,
          4,
          3,
          5,
          5,
          7,
          5,
          3,
          4,
          4,
          3,
          8,
          5,
          6,
          5,
          3,
          4,
          3,
          10,
          4,
          4,
          4,
          5,
          5,
          3,
          3,
          8,
          4,
          4,
          9,
          5,
          5,
          3,
          3,
          10,
          4,
          4,
          5,
          5,
          5,
          3,
          3,
          5,
          4,
          4,
          8,
          5,
          5,
          3,
          3,
          8,
          4,
          4,
          9,
          5,
          5,
          3,
          3,
          8,
          4,
          4,
          9,
          5,
          5,
          3,
          3,
          5,
          4,
          4,
          7,
          5,
          5,
          3,
          3,
          10,
          4,
          4,
          7,
          5,
          5,
          3,
          3,
          5,
          4,
          4,
          9,
          5,
          5,
          3,
          3,
          7,
          4,
          4,
          5,
          5,
          5,
          3
        ],
        "losses": [
          1,
          1,
          1,
          3,
          1,
          2,
          3,
          2,
          1,
          1,
          1,
          3,
          1,
          2,
          3,
          2,
          1,
          1,
          1,
          3,
          1,
          3,
          3,
          2,
          1,
          1,
          1,
          3,
          1,
          3,
          3,
          2,
          1,
          1,
          1,
          3,
          1,
          3,
          3,
          2,
          1,
          1,
          1,
          3,
          1,
          3,
          3,
          2,
          1,
          1,
          1,
          3,
          1,
          3,
          5,
          2,
          1,
          1,
          3,
          3,
          2,
          2,
          1,
          1,
          1,
          1,
          3,
          3,
          2,
          2,
          1,
          1,
          1,
          1,
          3,
          3,
          2,
          2,
          1,
          1,
          1,
          3,
          3,
          3,
          2,
          2,
          1,
          1,
          1,
          3,
          3,
          3,
          2,
          2,
          1,
          1,
          1,
          3,
          3,
          3,
          2,
          2,
          1,
          1,
          1,
          3,
          3,
          3,
          3,
          2,
          1,
          1,
          1,
          3,
          3,
          3,
          3,
          2,
          1,
          1,
          2,
          3,
          2,
          3,
          1,
          1,
          1,
          1,
          2,
          3,
          2,
          3,
          1,
          1,
          1,
          1,
          2,
          3,
          2,
          3,
          1,
          1,
          1,
          1,
          2,
          3,
          2,
          3,
          1,
          1,
          1,
          1,
          2,
          3,
          2,
          3,
          1,
          1,
          1,
          1,
          2,
          3,
          2,
          3,
          1,
          1,
          1,
          1,
          1,
          3,
          3,
          1,
          2,
          1,
          2,
          1,
          1,
          3,
          3,
          1,
          2,
          1,
          2,
          1,
          1,
          3,
          3,
          1,
          2,
          1,
          2,
          1,
          1,
          3,
          3,
          1,
          2,
          1,
          2,
          1,
          1,
          3,
          3,
          1,
          2,
          1,
          2,
          1,
          1,
          3,
          1,
          2,
          1,
          2,
          1,
          1,
          3,
          1,
          2,
          3,
          2,
          1,
          1,
          3,
          1,
          2,
          3,
          2,
          1,
          1,
          5,
          1,
          2,
          3,
          2,
          1,
          1,
          5,
          1,
          2,
          3,
          2,
          1,
          1,
          5,
          1,
          2,
          3,
          2,
          1,
          1,
          5,
          1,
          2,
          3,
          2,
          1,
          1,
          5,
          1,
          2,
          3,
          2,
          1,
          3,
          1,
          1,
          2,
          2,
          1,
          1,
          3,
          3,
          1,
          1,
          2,
          2,
          1,
          1,
          3,
          3,
          1,
          1,
          2,
          2,
          1,
          1,
          3,
          3,
          1,
          1,
          2,
          2,
          1,
          1,
          3,
          3,
          1,
          1,
          2,
          2,
          1,
          1,
          3,
          3,
          1,
          1,
          2,
          2,
          1,
          1,
          3,
          3,
          1,
          1,
          2,
          2,
          1,
          1,
          3,
          3,
          1,
          1,
          2,
          2,
          1,
          1,
          3,
          3,
          1,
          2,
          1,
          3,
          1,
          2,
          1,
          3,
          1,
          2,
          1,
          3,
          1,
          2,
          1,
          3,
          1,
          2,
          1,
          3,
          1,
          2,
          1,
          3,
          1,
          2,
          1,
          3,
          3,
          2,
          1,
          3,
          1,
          2,
          1,
          3,
          3,
          2,
          1,
          3,
          1,
          2,
          1,
          3,
          3,
          2,
          1,
          3,
          1,
          2,
          1,
          3,
          2,
          1,
          3,
          1,
          2,
          1,
          3,
          2,
          1,
          3,
          1,
          2,
          1,
          3,
          2,
          1,
          3,
          1,
          2,
          1,
          3,
          2,
          1,
          3,
          1,
          2,
          1,
          3,
          2,
          1,
          3,
          1,
          2,
          1,
          3,
          2,
          1,
          3,
          1,
          2,
          1,
          3,
          2,
          1,
          1,
          1,
          2,
          1,
          3,
          3,
          1,
          2,
          1,
          1,
          2,
          1,
          3,
          3,
          1,
          2,
          1,
          1,
          2,
          1,
          3,
          3,
          1,
          2,
          1,
          1,
          2,
          1,
          3,
          3,
          1,
          2,
          1,
          3,
          2,
          1,
          3,
          3,
          1,
          2,
          1,
          3,
          2,
          1,
          3,
          3,
          1,
          2,
          1,
          3,
          2,
          1,
          3,
          3,
          1,
          2,
          1,
          3,
          2,
          1,
          3,
          3,
          1,
          2,
          1,
          3,
          2,
          1,
          3,
          3,
          1,
          2,
          1,
          3,
          2,
          1,
          3,
          3,
          1,
          2,
          3,
          2,
          1,
          3,
          2,
          1,
          1,
          1,
          3,
          2,
          1,
          3,
          2,
          1,
          1,
          1,
          3,
          2,
          1,
          3,
          2,
          1,
          1,
          1,
          3,
          2,
          1,
          3,
          2,
          1,
          1,
          1,
          3,
          2,
          1,
          3,
          2,
          1,
          1,
          1,
          3,
          2,
          1,
          3,
          2,
          1,
          1,
          1,
          2,
          3,
          2,
          1,
          3,
          1,
          1,
          1,
          2,
          3,
          2,
          1,
          3,
          1,
          5,
          1,
          2,
          3,
          2,
          1,
          3,
          1,
          5,
          1,
          2,
          3,
          2,
          1,
          3,
          1,
          5,
          1,
          2,
          3,
          2,
          1,
          3,
          1,
          5,
          1,
          2,
          3,
          2,
          1,
          5,
          1,
          5,
          1,
          2,
          3,
          2,
          1,
          5,
          1,
          5,
          1,
          2,
          3,
          2,
          1,
          5,
          1,
          5,
          1,
          2,
          3,
          2,
          1,
          5,
          1,
          5,
          1,
          2,
          3,
          2,
          1,
          5,
          1,
          5,
          1,
          2,
          3,
          2,
          1,
          5,
          1,
          5,
          1,
          2,
          3,
          2,
          1,
          5,
          1,
          5,
          1,
          2,
          3,
          2,
          1,
          5,
          1,
          5,
          1,
          2,
          3,
          2,
          1,
          5,
          1,
          5,
          1,
          2,
          3,
          2,
          1,
          5,
          1,
          5,
          1,
          2,
          3,
          2,
          1,
          5,
          1,
          5,
          1,
          2,
          3,
          2,
          1,
          5,
          1,
          5,
          1,
          2,
          3,
          2,
          1,
          5,
          1,
          5,
          1,
          2,
          3,
          2,
          1,
          5,
          1,
          5,
          1,
          1,
          1,
          1,
          2,
          2,
          1,
          3,
          3,
          1,
          1,
          1,
          2,
          2,
          1,
          3,
          3,
          1,
          1,
          5,
          2,
          2,
          1,
          3,
          3,
          1,
          1,
          5,
          2,
          2,
          1,
          3,
          3,
          1,
          1,
          5,
          2,
          2,
          1,
          3,
          3,
          1,
          1,
          5,
          2,
          2,
          1,
          3,
          3,
          1,
          1,
          5,
          2,
          2,
          1,
          3,
          3,
          1,
          1,
          5,
          2,
          2,
          1,
          3,
          3,
          1,
          1,
          5,
          2,
          2,
          1,
          3,
          3,
          1,
          1,
          5,
          2,
          2,
          1,
          3,
          3,
          1,
          1,
          5,
          2,
          3,
          1,
          3,
          3,
          1,
          3,
          1,
          3,
          2,
          2,
          1,
          1,
          1,
          3,
          3,
          3,
          2,
          2,
          1,
          1,
          1,
          3,
          3,
          3,
          2,
          2,
          1,
          1,
          1,
          3,
          3,
          3,
          2,
          2,
          1,
          1,
          1,
          3,
          3,
          3,
          2,
          2,
          1,
          1,
          1,
          3,
          3,
          3,
          2,
          2,
          1,
          1,
          1,
          3,
          3,
          3,
          2,
          2,
          1,
          1,
          1,
          3,
          3,
          3,
          2,
          2,
          1,
          1,
          1,
          1,
          1,
          1,
          3,
          2,
          2,
          3,
          1,
          1,
          1,
          1,
          3,
          2,
          2,
          3,
          1,
          1,
          1,
          1,
          3,
          2,
          2,
          3,
          1,
          1,
          1,
          1,
          3,
          2,
          2,
          3,
          1,
          1,
          1,
          1,
          3,
          2,
          2,
          3,
          1,
          1,
          1,
          1,
          3,
          2,
          2,
          3,
          1,
          1,
          1,
          1,
          3,
          2,
          2,
          3,
          1,
          1,
          1,
          1,
          3,
          2,
          2,
          3,
          3,
          1,
          1,
          3,
          2,
          1,
          1,
          2,
          3,
          1,
          1,
          3,
          2,
          1,
          1,
          2,
          3,
          1,
          1,
          3,
          2,
          1,
          1,
          2,
          3,
          1,
          1,
          3,
          2,
          1,
          1,
          2,
          3,
          1,
          1,
          3,
          2,
          1,
          1,
          2,
          3,
          1,
          1,
          3,
          2,
          1,
          1,
          2,
          3,
          1,
          1,
          3,
          2,
          1,
          1,
          2,
          3,
          1,
          1,
          3,
          2,
          1,
          1,
          2,
          3,
          1,
          1,
          3,
          2,
          1,
          1,
          2,
          3,
          1,
          1,
          3,
          2,
          1,
          1,
          2,
          2,
          1,
          1,
          3,
          1,
          1,
          3,
          2,
          2,
          1,
          1,
          3,
          1,
          1,
          3,
          2,
          2,
          1,
          1,
          3,
          1,
          1,
          3,
          2,
          2,
          1,
          1,
          3,
          1,
          1,
          3,
          2,
          2,
          1,
          1,
          3,
          1,
          1,
          3,
          2,
          2,
          1,
          1,
          3,
          5,
          1,
          3,
          2,
          2,
          1,
          1,
          3,
          5,
          1,
          3,
          2,
          3,
          1,
          1,
          3,
          5,
          1,
          3,
          2,
          1,
          2,
          3,
          1,
          3,
          2,
          1,
          1,
          5,
          2,
          3,
          1,
          3,
          2,
          1,
          1,
          5,
          2,
          3,
          1,
          3,
          2,
          1,
          1,
          5,
          2,
          3,
          1,
          3,
          2,
          1,
          1,
          5,
          2,
          3,
          1,
          3,
          2,
          1,
          1,
          5,
          2,
          3,
          1,
          3,
          2,
          1,
          1,
          3,
          2,
          1,
          1,
          1,
          3,
          2,
          1,
          3,
          2,
          1,
          1,
          1,
          3,
          2,
          1,
          3,
          2,
          1,
          1,
          1,
          3,
          2,
          1,
          3,
          2,
          1,
          1,
          1,
          3,
          2,
          1,
          3,
          3,
          1,
          1,
          1,
          3,
          2,
          1,
          3,
          3,
          1,
          1,
          1,
          3,
          2,
          1,
          3,
          3,
          1,
          1,
          1,
          3,
          2,
          1,
          3,
          3,
          1,
          1,
          1,
          3,
          2,
          1,
          3,
          3,
          1,
          1,
          1,
          3,
          2,
          1,
          1,
          3,
          2,
          1,
          1,
          3,
          2,
          1,
          1,
          3,
          2,
          1,
          1,
          3,
          2,
          1,
          1,
          2,
          1,
          1,
          3,
          2,
          1,
          1,
          2,
          1,
          1,
          3,
          2,
          1,
          1,
          2,
          1,
          1,
          3,
          2,
          1,
          1,
          3,
          1,
          1,
          3,
          2,
          1,
          1,
          3,
          1,
          1,
          3,
          2,
          1,
          1,
          3,
          1,
          1,
          3,
          2,
          1,
          5,
          3,
          1,
          1,
          3,
          2,
          1,
          5,
          5,
          1,
          1,
          3,
          2,
          3,
          5,
          5,
          1,
          1,
          3,
          2,
          3,
          1,
          2,
          1,
          1,
          2,
          1,
          3,
          3,
          1,
          2,
          1,
          1,
          2,
          1,
          3,
          3,
          1,
          2,
          1,
          1,
          2,
          1,
          3,
          3,
          1,
          2,
          1,
          1,
          2,
          1,
          3,
          3,
          1,
          2,
          1,
          1,
          2,
          1,
          3,
          3,
          1,
          2,
          1,
          1,
          2,
          1,
          3,
          3,
          1,
          2,
          1,
          1,
          2,
          1,
          3,
          3,
          1,
          2,
          1,
          1,
          2,
          1,
          3,
          3,
          1,
          2,
          1,
          1,
          2,
          1,
          3,
          3,
          1,
          2,
          1,
          1,
          3,
          1,
          3,
          3,
          1,
          2,
          1,
          5,
          3,
          1,
          3,
          3,
          2,
          1,
          1,
          2,
          3,
          3,
          1,
          1,
          2,
          1,
          1,
          2,
          3,
          3,
          1,
          1,
          2,
          1,
          1,
          2,
          3,
          3,
          1,
          1,
          2,
          1,
          3,
          2,
          3,
          3,
          1,
          1,
          2,
          1,
          3,
          2,
          3,
          3,
          1,
          1,
          2,
          1,
          3,
          2,
          3,
          3,
          1,
          5,
          1,
          1,
          1,
          2,
          3,
          3,
          2,
          1,
          1,
          1,
          1,
          2,
          3,
          3,
          2,
          1,
          1,
          1,
          1,
          2,
          3,
          3,
          2,
          1,
          1,
          1,
          1,
          2,
          3,
          3,
          2,
          1,
          1,
          1,
          1,
          2,
          3,
          3,
          2,
          1,
          1,
          1,
          1,
          2,
          3,
          3,
          2,
          1,
          1,
          1,
          1,
          2,
          3,
          3,
          2,
          1,
          1,
          1,
          1,
          2,
          3,
          3,
          2,
          1,
          1,
          1,
          1,
          2,
          3,
          3,
          2,
          1,
          1,
          1,
          1,
          2,
          3,
          3,
          2,
          1
        ]
      },
      "nerve_changes": {
        "gains": [],
        "losses": []
      },
      "interactions": {
        "interferences": 0,
        "defenses": 0,
        "blocks": 0
      },
      "effect_thefts": {
        "total_thefts": 0
      }
    },
    "balance_analysis": {
      "game_length_stats": {
        "min_turns": 51,
        "max_turns": 153,
        "avg_turns": 78.6,
        "median_turns": 80
      },
      "win_balance": {
        "total_winners": 20,
        "unique_winners": 8,
        "win_distribution": {
          "Художник-фрилансер": 4,
          "Предприниматель": 5,
          "Официант": 3,
          "Курьер": 2,
          "Жена/муж испанца": 2,
          "IT-шник": 1,
          "Студент": 2,
          "Пенсионер": 1
        },
        "most_successful_profile": [
          "Предприниматель",
          5
        ]
      },
      "success_rates": {
        "avg_document_success_rate": 0,
        "avg_challenge_success_rate": 0
      }
    }
  },
  "recent_games": [
    {
      "game_id": 1,
      "winner": "Художник-фрилансер",
      "end_reason": "win",
      "turns": 58,
      "duration": 0.0017709732055664062
    },
    {
      "game_id": 2,
      "winner": "Предприниматель",
      "end_reason": "win",
      "turns": 68,
      "duration": 0.0060498714447021484
    },
    {
      "game_id": 3,
      "winner": "Официант",
      "end_reason": "win",
      "turns": 51,
      "duration": 0.04571986198425293
    },
    {
      "game_id": 4,
      "winner": "Официант",
      "end_reason": "win",
      "turns": 101,
      "duration": 0.04891395568847656
    },
    {
      "game_id": 5,
      "winner": "Курьер",
      "end_reason": "win",
      "turns": 68,
      "duration": 0.0914146900177002
    },
    {
      "game_id": 6,
      "winner": "Жена/муж испанца",
      "end_reason": "win",
      "turns": 102,
      "duration": 0.09424281120300293
    },
    {
      "game_id": 7,
      "winner": "IT-шник",
      "end_reason": "win",
      "turns": 85,
      "duration": 0.1406106948852539
    },
    {
      "game_id": 8,
      "winner": "Художник-фрилансер",
      "end_reason": "win",
      "turns": 51,
      "duration": 0.14200592041015625
    },
    {
      "game_id": 9,
      "winner": "Курьер",
      "end_reason": "win",
      "turns": 153,
      "duration": 0.18753695487976074
    },
    {
      "game_id": 10,
      "winner": "Предприниматель",
      "end_reason": "win",
      "turns": 96,
      "duration": 0.23221778869628906
    },
    {
      "game_id": 11,
      "winner": "Предприниматель",
      "end_reason": "win",
      "turns": 66,
      "duration": 0.2340528964996338
    },
    {
      "game_id": 12,
      "winner": "Художник-фрилансер",
      "end_reason": "win",
      "turns": 68,
      "duration": 0.2781178951263428
    },
    {
      "game_id": 13,
      "winner": "Официант",
      "end_reason": "win",
      "turns": 88,
      "duration": 0.2812988758087158
    },
    {
      "game_id": 14,
      "winner": "Студент",
      "end_reason": "win",
      "turns": 67,
      "duration": 0.3249187469482422
    },
    {
      "game_id": 15,
      "winner": "Предприниматель",
      "end_reason": "win",
      "turns": 53,
      "duration": 0.3270227909088135
    },
    {
      "game_id": 16,
      "winner": "Пенсионер",
      "end_reason": "win",
      "turns": 80,
      "duration": 0.3292076587677002
    },
    {
      "game_id": 17,
      "winner": "Студент",
      "end_reason": "win",
      "turns": 87,
      "duration": 0.38596582412719727
    },
    {
      "game_id": 18,
      "winner": "Художник-фрилансер",
      "end_reason": "win",
      "turns": 94,
      "duration": 0.43279004096984863
    },
    {
      "game_id": 19,
      "winner": "Предприниматель",
      "end_reason": "win",
      "turns": 53,
      "duration": 0.4344828128814697
    },
    {
      "game_id": 20,
      "winner": "Жена/муж испанца",
      "end_reason": "win",
      "turns": 83,
      "duration": 0.43946385383605957
    }
  ]
}